fetching/__init__.py
fetching/__main__.py
fetching/fetching.py
sandbox/__init__.py
sandbox/f.py
sandbox/j.py
sandbox/methods_test.py
sandbox/req_ex.py
sandbox/splt.py
sandbox/classes/__init__.py
sandbox/classes/dep_one.py
fetching-0.2.0.dist-info/LICENSE
fetching-0.2.0.dist-info/METADATA
fetching-0.2.0.dist-info/WHEEL
fetching-0.2.0.dist-info/top_level.txt
fetching-0.2.0.dist-info/RECORD
