Metadata-Version: 2.1
Name: fetching
Version: 0.2.0
Summary: Python tool for automatically wrapping multiple (possibly private) Python libraries into a single portable module file.
Home-page: https://github.com/nthparty/fetching
Author: bengetch
Author-email: bengetch@gmail.com
License: MIT
Platform: UNKNOWN
Requires-Python: >=3.8
Requires-Dist: PyGithub
